<?xml version="1.0" encoding="UTF-8"?>
<persistence version="2.2"
	xmlns="http://xmlns.jcp.org/xml/ns/persistence"
	xmlns:xsi="http://www.w3.org/2001/XMLSchema-instance"
	xsi:schemaLocation="http://xmlns.jcp.org/xml/ns/persistence http://xmlns.jcp.org/xml/ns/persistence/persistence_2_2.xsd">
	<persistence-unit name="Farmacia">
		<class>br.unitins.tp1.aula2.model.Usuario</class>
		<properties>
			<!-- DB Driver -->
			<property name="javax.persistence.jdbc.driver"
				value="org.postgresql.Driver" />

			<!-- BD Name -->
			<property name="javax.persistence.jdbc.url"
				value="jdbc:postgresql://127.0.0.1:5432/cadastrousuario" />

			<!-- DB User -->
			<property name="javax.persistence.jdbc.user"
				value="_admin" />

			<!-- DB Password -->
			<property name="javax.persistence.jdbc.password"
				value="admin" />

			<!-- DB Dialect -->
			<property name="hibernate.dialect"
				value="org.hibernate.dialect.PostgreSQLDialect" />

			<!-- create / create-drop / update / none -->
			<property name="hibernate.hbm2ddl.auto" value="update" />

			<!-- Show SQL in console -->
			<property name="hibernate.show_sql" value="true" />

			<!-- Show SQL formatted -->
			<property name="hibernate.format_sql" value="true" />
		</properties>

	</persistence-unit>
</persistence>